numerosprimostest/__init__.py
numerosprimostest-1.0.dist-info/LICENSE
numerosprimostest-1.0.dist-info/METADATA
numerosprimostest-1.0.dist-info/WHEEL
numerosprimostest-1.0.dist-info/top_level.txt
numerosprimostest-1.0.dist-info/RECORD
